kivymin/__init__.py
kivymin/kivymin.py
kivymin-0.3.0.dist-info/METADATA
kivymin-0.3.0.dist-info/WHEEL
kivymin-0.3.0.dist-info/top_level.txt
kivymin-0.3.0.dist-info/RECORD
